simple_neural_works/__init__.py
simple_neural_works/main.py
simple_neural_works/setup.py
simple_neural_works-2.0.2.dist-info/METADATA
simple_neural_works-2.0.2.dist-info/WHEEL
simple_neural_works-2.0.2.dist-info/top_level.txt
simple_neural_works-2.0.2.dist-info/RECORD
