Metadata-Version: 2.1
Name: simple_neural_works
Version: 2.0.2
Summary: This is the simplest educational module for quick work with neural networks.
Home-page: https://github.com/TwentyOneError/simple_neural_works
Author: TwentyOneError
Author-email: ourmail20210422@gmail.com
Project-URL: GitHub, https://github.com/TwentyOneError
Keywords: neural networks simple backpropagation regularization Leaky-ReLu
Classifier: Programming Language :: Python :: 3.11
Classifier: Operating System :: OS Independent
Requires-Python: >=3.8
Requires-Dist: Pillow (>=8.2.0)
Requires-Dist: numpy
